colorful_terminal/__init__.py
colorful_terminal/definitions.py
colorful_terminal-0.1.7.dist-info/licenses/LICENSE
colorful_terminal-0.1.7.dist-info/METADATA
colorful_terminal-0.1.7.dist-info/WHEEL
colorful_terminal-0.1.7.dist-info/top_level.txt
colorful_terminal-0.1.7.dist-info/RECORD
