Metadata-Version: 2.4
Name: colorful_terminal
Version: 0.1.7
Summary: Print with color, style your output and take full control of your terminal.
Home-page: https://github.com/ICreedenI/colorful_terminal
Author: André Herber
Author-email: andre.herber.programming@gmail.com
Keywords: python,print,color,colour,colored,coloured,rainbow,terminal,console,colorama
Classifier: Development Status :: 2 - Pre-Alpha
Classifier: Environment :: Console
Classifier: Intended Audience :: Developers
Classifier: Programming Language :: Python :: 3
Classifier: Programming Language :: Python :: 3.9
Classifier: Programming Language :: Python :: 3.10
Classifier: License :: OSI Approved :: MIT License
Classifier: Operating System :: Microsoft :: Windows
Classifier: Topic :: Terminals
License-File: LICENSE
Dynamic: author
Dynamic: author-email
Dynamic: classifier
Dynamic: description
Dynamic: description-content-type
Dynamic: home-page
Dynamic: keywords
Dynamic: license-file
Dynamic: summary
